setup.py
Dockerizer/__init__.py
Dockerizer/_version.py
Dockerizer/bootstrap.py
Dockerizer/clean.py
Dockerizer/config.py
Dockerizer/dockerize.py
Dockerizer/morning_pull.py
Dockerizer/reboot.py
Dockerizer/reset.py
Dockerizer.egg-info/PKG-INFO
Dockerizer.egg-info/SOURCES.txt
Dockerizer.egg-info/dependency_links.txt
Dockerizer.egg-info/entry_points.txt
Dockerizer.egg-info/requires.txt
Dockerizer.egg-info/top_level.txt
Dockerizer/compose/__init__.py
Dockerizer/compose/commands.py
Dockerizer/compose/compose.py
Dockerizer/docker/__init__.py
Dockerizer/docker/commands.py
Dockerizer/docker/docker.py
Dockerizer/docker/gui.py
Dockerizer/docker/run.py