Metadata-Version: 1.0
Name: Dockerizer
Version: 1.2.2
Summary: Docker CLI wrapper with GUI for quickly Dockerizing applications.
Home-page: https://github.com/mrstephenneal/Dockerizer
Author: Stephen Neal
Author-email: stephen@stephenneal.net
License: UNKNOWN
Platform: UNKNOWN
